spoqa_requests_backoff.py
spoqa_requests_backoff-0.1.1.dist-info/LICENSE
spoqa_requests_backoff-0.1.1.dist-info/WHEEL
spoqa_requests_backoff-0.1.1.dist-info/METADATA
spoqa_requests_backoff-0.1.1.dist-info/RECORD
